{
  "status": "OTEVIRACI DOBA",
  "days": [
    {
      "weekday": "P?",
      "date": "17.4",
      "houram": "10:00-12:00",
      "hourpm": "13:00-18:00"
    },
    {
      "weekday": "So",
      "date": "18.4",
      "houram": "10:00-12:00",
      "hourpm": "13:00-18:00"
    },
    {
      "weekday": "Ne",
      "date": "19.4",
      "houram": "10:00-12:00",
      "hourpm": "13:00-18:00"
    },
    {
      "weekday": "Po",
      "date": "20.4",
      "houram": "10:00-12:00",
      "hourpm": "13:00-18:00"
    },
    {
      "weekday": "?t",
      "date": "21.4",
      "houram": "10:00-18:00",
      "hourpm": ""
    },
    {
      "weekday": "St",
      "date": "22.4",
      "houram": "10:00-12:00",
      "hourpm": "13:00-18:00"
    },
    {
      "weekday": "?t",
      "date": "23.4",
      "houram": "10:00-19:00",
      "hourpm": ""
    },
    {
      "weekday": "P?",
      "date": "24.4",
      "houram": "10:00-12:00",
      "hourpm": "13:00-18:00"
    },
    {
      "weekday": "So",
      "date": "25.4",
      "houram": "10:00-12:00",
      "hourpm": "13:00-18:00"
    },
    {
      "weekday": "Ne",
      "date": "26.4",
      "houram": "10:00-12:00",
      "hourpm": "13:00-18:00"
    },
    {
      "weekday": "Po",
      "date": "27.4",
      "houram": "10:00-12:00",
      "hourpm": "13:00-18:00"
    },
    {
      "weekday": "?t",
      "date": "28.4",
      "houram": "10:00-12:00",
      "hourpm": "13:00-18:00"
    },
    {
      "weekday": "St",
      "date": "29.4",
      "houram": "10:00-12:00",
      "hourpm": "13:00-18:00"
    },
    {
      "weekday": "?t",
      "date": "30.4",
      "houram": "10:00-12:00",
      "hourpm": "13:00-18:00"
    },
    {
      "weekday": "P?",
      "date": "1.5",
      "houram": "10:00-12:00",
      "hourpm": "13:00-18:00"
    },
    {
      "weekday": "So",
      "date": "2.5",
      "houram": "10:00-12:00",
      "hourpm": "13:00-18:00"
    },
    {
      "weekday": "Ne",
      "date": "3.5",
      "houram": "10:00-12:00",
      "hourpm": "13:00-18:00"
    },
    {
      "weekday": "Po",
      "date": "4.5",
      "houram": "10:00-12:00",
      "hourpm": "13:00-18:00"
    },
    {
      "weekday": "?t",
      "date": "5.5",
      "houram": "10:00-12:00",
      "hourpm": "13:00-18:00"
    },
    {
      "weekday": "St",
      "date": "6.5",
      "houram": "10:00-12:00",
      "hourpm": "13:00-18:00"
    },
    {
      "weekday": "?t",
      "date": "7.5",
      "houram": "10:00-12:00",
      "hourpm": "13:00-18:00"
    }
  ]
}